setup.cfg
setup.py
glossika.egg-info/PKG-INFO
glossika.egg-info/SOURCES.txt
glossika.egg-info/dependency_links.txt
glossika.egg-info/not-zip-safe
glossika.egg-info/requires.txt
glossika.egg-info/top_level.txt
speech/speech.py