Metadata-Version: 1.1
Name: glossika
Version: 1.0
Summary: Draw pitch for your audio file
Home-page: UNKNOWN
Author: Peter
Author-email: peter_wang@glossika.com
License: MIT
Platform: UNKNOWN
Classifier: Development Status :: 5 - Production/Stable
Classifier: License :: OSI Approved :: MIT License
Classifier: Programming Language :: Python :: 3.5
Classifier: Programming Language :: Python :: 3.6
